setup.py
imageSegmentAnalyzer/__init__.py
imageSegmentAnalyzer/image.py
imageSegmentAnalyzer/io.py
imageSegmentAnalyzer.egg-info/PKG-INFO
imageSegmentAnalyzer.egg-info/SOURCES.txt
imageSegmentAnalyzer.egg-info/dependency_links.txt
imageSegmentAnalyzer.egg-info/not-zip-safe
imageSegmentAnalyzer.egg-info/requires.txt
imageSegmentAnalyzer.egg-info/top_level.txt
imageSegmentAnalyzer/tests/__init__.py
imageSegmentAnalyzer/tests/test_image_class.py