Metadata-Version: 1.0
Name: imageSegmentAnalyzer
Version: 0.15
Summary: For segmenting and analyzing images
Home-page: https://github.com/CSSFrancis/empyer
Author: CSSFrancis
Author-email: csfrancis@wisc.edu
License: UNKNOWN
Keywords: Image analysis
Platform: UNKNOWN
